Metadata-Version: 2.1
Name: resume-module
Version: 0.3
Summary: A module to generate and save professional resumes as PDFs using OpenAI
Home-page: https://github.com/ibrahim-string/resume_module
Author: Your Name
Author-email: string2025@gmail.com
Classifier: Programming Language :: Python :: 3
Classifier: License :: OSI Approved :: MIT License
Classifier: Operating System :: OS Independent
Requires-Python: >=3.6
License-File: license.txt
Requires-Dist: openai
Requires-Dist: fpdf
Requires-Dist: python-dotenv
